.gitignore
.project
CHANGES.txt
COPYRIGHT.txt
LICENSE.txt
README.txt
buildout.cfg
facebook.ini
setup.cfg
setup.py
yasso-demo.ini
src/oauth2sample/__init__.py
src/oauth2sample/models.py
src/oauth2sample/views.py
src/oauth2sample.egg-info/PKG-INFO
src/oauth2sample.egg-info/SOURCES.txt
src/oauth2sample.egg-info/dependency_links.txt
src/oauth2sample.egg-info/entry_points.txt
src/oauth2sample.egg-info/not-zip-safe
src/oauth2sample.egg-info/requires.txt
src/oauth2sample.egg-info/top_level.txt
src/oauth2sample/static/favicon.ico
src/oauth2sample/static/footerbg.png
src/oauth2sample/static/headerbg.png
src/oauth2sample/static/ie6.css
src/oauth2sample/static/middlebg.png
src/oauth2sample/static/pylons.css
src/oauth2sample/static/pyramid-small.png
src/oauth2sample/static/pyramid.png
src/oauth2sample/static/transparent.gif
src/oauth2sample/templates/home.pt