Metadata-Version: 1.0
Name: oauth2sample
Version: 0.1
Summary: Sample OAuth2 Client
Home-page: https://github.com/hathawsh/oauth2sample
Author: Shane Hathaway
Author-email: shane@hathawaymix.org
License: BSD-derived (http://www.repoze.org/LICENSE.txt)
Keywords: web pylons pyramid oauth oauth2 yasso
Platform: UNKNOWN
Classifier: Development Status :: 3 - Alpha
Classifier: Intended Audience :: Developers
Classifier: Programming Language :: Python
Classifier: Framework :: Pylons
Classifier: Topic :: Internet :: WWW/HTTP
Classifier: Topic :: Internet :: WWW/HTTP :: WSGI :: Application
